image_diversity/__init__.py
image_diversity/__main__.py
image_diversity/clip_metrcis.py
image_diversity/inception.py
image_diversity/inception_metrics.py
image_diversity/utils.py
image_diversity/clip/__init__.py
image_diversity/clip/bpe_simple_vocab_16e6.txt.gz
image_diversity/clip/clip.py
image_diversity/clip/model.py
image_diversity/clip/simple_tokenizer.py
image_diversity-0.1.6.dist-info/LICENSE
image_diversity-0.1.6.dist-info/METADATA
image_diversity-0.1.6.dist-info/WHEEL
image_diversity-0.1.6.dist-info/top_level.txt
image_diversity-0.1.6.dist-info/RECORD
