Metadata-Version: 2.1
Name: image_diversity
Version: 0.1.6
Summary: A package for computing entropy-based diversity measures on image sets
Author-email: Francisco Ibarrola <francisco.ibarrola@outlook.com>
Project-URL: Homepage, https://github.com/fibarrola/image_diversity
Requires-Python: >=3.8
License-File: LICENSE
Requires-Dist: torch >=1.7.1
Requires-Dist: torchvision
Requires-Dist: ftfy
Requires-Dist: regex
Requires-Dist: tqdm
Requires-Dist: scipy
